quickrpc/QtTransports.py
quickrpc/__init__.py
quickrpc/action_queue.py
quickrpc/announcer_api.py
quickrpc/bus_transport.py
quickrpc/codecs.py
quickrpc/echo_api.py
quickrpc/network_transports.py
quickrpc/promise.py
quickrpc/remote_api.py
quickrpc/security.py
quickrpc/terse_codec.py
quickrpc/transports.py
quickrpc/util.py
quickrpc-0.1.0.dist-info/LICENSE
quickrpc-0.1.0.dist-info/METADATA
quickrpc-0.1.0.dist-info/WHEEL
quickrpc-0.1.0.dist-info/top_level.txt
quickrpc-0.1.0.dist-info/zip-safe
quickrpc-0.1.0.dist-info/RECORD
