Metadata-Version: 2.1
Name: quickrpc
Version: 0.1.0
Summary: Small, interoperable, automagic RPC library.
Home-page: http://github.com/loehnertj/quickrpc
Author: Johannes Loehnert
Author-email: loehnert.kde@gmx.de
License: MIT
Platform: UNKNOWN
Classifier: Development Status :: 3 - Alpha
Classifier: License :: OSI Approved :: MIT License
Classifier: Programming Language :: Python :: 3.6
Classifier: Topic :: System :: Networking
Requires-Python: >3.0
